webint_ai/__init__.py
webint_ai/templates/__init__.py
webint_ai/templates/chat.html
webint_ai/templates/chat_response.html
webint_ai/templates/index.html
webint_ai-0.0.5.dist-info/METADATA
webint_ai-0.0.5.dist-info/entry_points.txt
webint_ai-0.0.5.dist-info/WHEEL
webint_ai-0.0.5.dist-info/RECORD
