Metadata-Version: 2.1
Name: webint-ai
Version: 0.0.5
Summary: manage your website's artificial intelligence
License: AGPL-3.0-or-later
Author: Angelo Gladding
Author-email: angelo@ragt.ag
Requires-Python: >=3.10,<3.11
Classifier: License :: OSI Approved :: GNU Affero General Public License v3 or later (AGPLv3+)
Classifier: Programming Language :: Python :: 3
Classifier: Programming Language :: Python :: 3.10
Requires-Dist: openai (>=0.27.2,<0.28.0)
Requires-Dist: webint (>=0.0)
